<root>﻿<page>010v</page>
<image>http://gallica.bnf.fr/ark:/12148/btv1b10500001g/f26.image</image>


<div>
<id>p010v_1</id>


<head>For painting in <m>oil</m> on <m>taffeta</m> without the <m>oil</m> running</head>


<ab>You have to make a layer of <m>batture</m>, made of "<m>colle forte</m>" soaked for 24 hours in <m>water</m> then gently boiled so it is not too strong. After, stir in a little <m>honey</m> to soften it and bring it all to a boil. And on top of this layer which will soon be dry, you will be able to paint in <m>oil</m><m>,</m> which will soften the layer even more, and which will also serve for a layer of <m>gold</m>. <m>Alum water</m> also keeps <m>oil</m> from running.</ab>
</div>


<div>
<id>p010v_2</id>


<head>Layer of <m>gold</m> leaf on <m>parchment</m> or <m>paper</m></head>


<ab>Make a very transparent <m>starch glue</m> with little body. And apply six or five layers, and when the last is almost dry, apply your <m>gold</m>.</ab>
 
</div>


<div>
<id>p010v_3</id>


<head>Cleaning <m>gold</m> leaf applied to iron</head>


<ab>Rub your weapons or other gilt objects with <m>dry <al>horse</al> dung</m>.</ab>
  
</div>


<div>
<id>p010v_4</id>


<head>Whitening <m>ceruse</m></head>


<ab>Boil some <m>eggs</m>, cut them in half and take the yellow out, and between the two halves of <m>egg white</m>, put a bit of <m>ceruse</m>, and stitch the two halves together with a thread. Then boil the stitched <m>egg</m> in some clear <m>water</m> and the <m>water</m> will become black and in this way the <m>ceruse</m> will stay purified. Some people cook it again over a fire and it becomes very white.</ab>
</div></root>