#ERROR:_Number_of_<div>_and_</div>_unbalanced#


<page>028v</page>
<image>http://gallica.bnf.fr/ark:/12148/btv1b10500001g/f62.image</image>
<div>
<id>p028v_1</id>
<head><pro>Pintiers</pro></head>


<ab>Ils estiment le meilleure <m>estain</m> celuy qui est en saulmon<lb/>
qui nha poinct este refondu despuys quil est venu de<lb/>
la mine pourceque les M{aistr}e{s} le refondent en grille<lb/>
poisant deux ou trois lb. pour mieux le debiter et<lb/>
vendre en detail Et en cestuy la bien souvent ilz y<lb/>
font du meslinge de restes a plats de souldure<lb/>
&amp; d<m>estain</m> commun Et pour cognoistre le meilleur cest<lb/>
le plus luisant qui est co{mm}e bruny Car il es plus douls<lb/>
Quelquefoys dans leurs saulmons ilz trouvent des<lb/>
pieces de <m>fer</m> des <m>pierres</m> &amp; semblables brouilleries<lb/>
pour tromper au poix L<m>estain</m> d<pl>angleterre</pl> est si dur<lb/>
que les <pro>minerons</pro> y mectent du <m>plomb</m> pour ladoulcir<lb/>
Celuy qui vient du coster d<pl>allemaigne</pl> est plus douls<lb/>
Communement les M{aistr}e{s} <pro>pintiers</pro> jures aulx bonnes villes<lb/>
mectent six lb. de <m>plomb</m> fin <del><del>sur</del></del> ou huict sur un quintal<lb/>
d<m>estaim</m> fin Les aultres qui travaillent aulx champs<lb/>
en mectent quinze ou 20 ou le plus quilz peuvent<lb/>
et pour couvrir la noirceur du <m>plomb</m> <del><del>il</del></del> et sa doulceur<lb/>
ilz y mectent de l<m>estaim de glace</m> 4 lb. sur quintal <figure>+</figure><lb/>
<del><del>po</del></del> qui blanchist &amp;affermist Et <del><del>bypes</del></del> <add>six ou huict lb.</add> de <m>rosette</m> pour<lb/>
rendre la vaisselle sonnante<lb/>
Pour mouler de plats &amp; escuelles ilz les font de <m>pierre<lb/>
<del><del>porte</del></del> morte</m> qui est <m>grais</m> &amp; les tournent &amp; polissent <del><del>aultour</del></del><lb/>
au tour Ils fondent leur <m>estaim</m> dans une cassolle <del><del>dest</del></del><lb/>
de <m>fer</m> a foeu de <m>charbons</m> Et avecq une cueillere de <m>fer</m><lb/>
qui tient <del><del>presque</del></del> la quantite suffisante pour un plat<lb/>
ilz gectent <del><del>des</del></del> dans leurs moules froids quilz tiennnent<lb/>
joincts &amp; serres entre les genoils Et bien tost ilz ouvrent<lb/>
les moules affin quilz ne seschaufent &amp; ayant oster le<lb/>
gect qui est du coste de la femelle &amp; qui se rompt aysem{ent}<lb/>
Puys avecq un linge qui trempe dans l<m>eau</m> quilz ont<lb/>
tousjours pres deus ilz frottent le milieu du revers de<lb/>
lescuelle &amp; aultour du bort affin quil senleve mieulx<lb/>
et en frottent la femelle molle</ab>
</div>
<note>


<margin>left-middle</margin>
<figure>+</figure> 
Quand l<m>estaing</m> est<lb/>
fin on y mect moings<lb/>
d<m>estaim de glace</m> sçavoir<lb/>
4 lb. pour quintal Mays<lb/>
se l<m>estaim</m> est bas cest<lb/>
a dire beaucoup allie<lb/>
de <m>plomb</m> on y mect bien<lb/>
cinq ou six lb. d<m>estaim<lb/>
de glace</m><lb/>
Sil ny ha guerres<lb/>
d<m>estaim de glace</m><lb/>
on mect co{mme}e deulx ou<lb/>
trois lb. pour quintal<lb/>
on mect huict lb. de<lb/>
<m>rosette</m> Mays sil y<lb/>
ha beaucoup d<m>estaim<lb/>
de glace</m> <del><del>on</del></del> co{mm}e 4 ou<lb/>
5 lb. on nen mect que<lb/>
six de <m>rosette</m> Et<lb/>
co{mmun}ement sur quintal<lb/>
d<m>estain</m> on mect x lb.<lb/>
de tous les deulx</note>
</div>


<div>
<id>p028v_2</id>
<head>Va au cinquiesme foeillet</head>
</div>