<root>﻿<page>123r</page> 
<image> #ERROR:_INSERT_LINK# </image>


</div>
<div>
<id>p123r_a1</id>
<head>Moyen di far correr <m>otnegra</m> </head>


<ab>P{rens} <m>arsenic blanc</m> deulx unces, 2 ℥<lb/>
<m>Orpiment</m> ou bien <m>arsenic jaulne</m> deulx unces, 2 ℥<lb/>
<m>Aes</m> <m>ustum</m> deulx unces ℥<lb/>
<m>Limaille de cuivre</m> fin mediocrem{ent} subtille, 2 ℥<lb/>
<m>Antimoyne</m>, 2 ℥<lb/>
<m>Sal gemme</m>, 2 ℥<lb/>
<m>Tartre crud</m>, 2 ℥<lb/>
<m>Suin de verre</m>, 2 ℥<lb/>
<m>Salpestre</m> la moictié, sçavoir 1 ℥ <lb/>
<m>Sel gros commun</m> fondu la moictié, 1 ℥<lb/>
<m>Sublimé</m> la moictié, 1 ℥<lb/>
<m>Borras</m> la moictié, 1 ℥<lb/>
<m>Sel armoniac</m> aultant que de <m>borras</m>, sçavoir 1 ℥ </ab>


<ab> P{rens} de ces materiaulx, des meilleurs que tu pourras trouver. Poisés<lb/>
les co{mm}e cy dessus est dict et les pilés separement, vous tenant<lb/>
le visaige bandé sur le nés &amp; la bouche, despuys les yeulx en<lb/>
bas, pour eviter l’exalation de <m>l’arsenic</m> <m>sublimé</m> &amp; <m>orpiment</m>.<lb/>
Meslés les bien tous ensemble, puys les mectés dans un bon<lb/>
crusol, qui soict si grand que les matieres y puissent avoir<lb/>
de vuyde la quarte ou cinquiesme partye. Couvrés le crusol<lb/>
d’un bon tuyle adapté en rond justement sur son ouverture. Et<lb/>
l’ayant lié de haut en bas et par les costés de fil de fer<lb/>
assés fort, lutés le avecq de la <m>terre fiens</m> ou <m>terre bourre</m>,<lb/>
de laquelle les <pro>fondeurs</pro> <pro>d’artiglerie</pro> se servent. Et en cela<lb/>
soyés curieux &amp; diligent, &amp; n’oubliés pas d’i mesler du <m>verre</m><lb/>
pilé parmy le luth, pour fortifier v{ost}re crusol, de maniere<lb/>
qu’il ne prene point de vent, car la matiere ne vauldroit<lb/>
gueres, à cause que les cinq derniers ingredients s’exhaleroient.</ab>


<note>
<margin>#ERROR:_NO_MARGIN_AVAILABLE#</margin>
Note qu’il te fault<lb/>
bien luter ton creuset<lb/>
affin que les matieres<lb/>
ne prenent vent, car<lb/>
elles s’exalleroient.</note>


<note>
<margin>#ERROR:_NO_MARGIN_AVAILABLE#</margin>
Lute bien ton crusol<lb/>
affin qu’il ne se rompe.<lb/>
Car s’il se rompt, les<lb/>
materiaulx s’evaporent<lb/>
et la fumée en est<lb/>
dangereuse. Si en 12<lb/>
heures il n’est fondu<lb/>
et meslé, il ne se fera<lb/>
point bien.</note>


<note>
<margin>#ERROR:_NO_MARGIN_AVAILABLE#</margin>
Les <pro>orfevres</pro><lb/>
qui ont cognois<lb/>
sance de ceste<lb/>
matiere vendent<lb/>
le denier d’icelle<lb/>
cinq sols aulx<lb/>
aultres <pro>orfevres.</pro><lb/>
Mesmement<lb/>
à ceulx qui<lb/>
travaillent de<lb/>
vaissele &amp; grosserie,<lb/>
car à la fin de<lb/>
leurs ouvraiges,<lb/>
ilz peuvent soulder<lb/>
sur la premiere<lb/>
souldure par le<lb/>
moyen de<lb/>
ceste mixture.<lb/>
En g{e}n{er}al,<lb/>
touts<lb/>
ceulx qui veulent<lb/>
mouler &amp; gecter<lb/>
quelque chose<lb/>
subtille. Ceste<lb/>
matiere ne doibt<lb/>
pas estre divulguée<lb/>
affin quil n’en soit<lb/>
point abusé.</note>


<note>
<margin>#ERROR:_NO_MARGIN_AVAILABLE#</margin>
<lb/>Le grain est co{mm}e<lb/>
de l’<m>acier</m> rompu.</note></root>